vsscunet/__init__.py
vsscunet/__main__.py
vsscunet/network_scunet.py
vsscunet/models/scunet_color_15.pth
vsscunet/models/scunet_color_25.pth
vsscunet/models/scunet_color_50.pth
vsscunet/models/scunet_color_real_gan.pth
vsscunet/models/scunet_color_real_psnr.pth
vsscunet-2.0.0.dist-info/METADATA
vsscunet-2.0.0.dist-info/WHEEL
vsscunet-2.0.0.dist-info/licenses/LICENSE
vsscunet-2.0.0.dist-info/RECORD
