Metadata-Version: 2.4
Name: vsscunet
Version: 2.0.0
Summary: SCUNet function for VapourSynth
Project-URL: Homepage, https://github.com/HolyWu/vs-scunet
Project-URL: Issues, https://github.com/HolyWu/vs-scunet/issues
Author-email: HolyWu <holywu@gmail.com>
License-File: LICENSE
Keywords: PyTorch,SCUNet,TensorRT,VapourSynth
Classifier: Environment :: GPU :: NVIDIA CUDA
Classifier: License :: OSI Approved :: Apache Software License
Classifier: Operating System :: OS Independent
Classifier: Programming Language :: Python :: 3
Classifier: Topic :: Multimedia :: Video
Requires-Python: >=3.10
Requires-Dist: einops
Requires-Dist: numpy
Requires-Dist: requests
Requires-Dist: timm
Requires-Dist: torch>=2.6.0.dev
Requires-Dist: tqdm
Requires-Dist: vapoursynth>=66
